Storm110ZhongwenWendang/README.md
Storm110ZhongwenWendang/__init__.py
Storm110ZhongwenWendang/__main__.py
Storm110ZhongwenWendang/file.epub
Storm110ZhongwenWendang/index.html
Storm110ZhongwenWendang/css/__init__.py
Storm110ZhongwenWendang/css/annotations.css
Storm110ZhongwenWendang/css/main.css
Storm110ZhongwenWendang/css/normalize.css
Storm110ZhongwenWendang/css/popup.css
Storm110ZhongwenWendang/font/__init__.py
Storm110ZhongwenWendang/font/fontello.eot
Storm110ZhongwenWendang/font/fontello.svg
Storm110ZhongwenWendang/font/fontello.ttf
Storm110ZhongwenWendang/font/fontello.woff
Storm110ZhongwenWendang/img/__init__.py
Storm110ZhongwenWendang/img/annotator-glyph-sprite.png
Storm110ZhongwenWendang/img/annotator-icon-sprite.png
Storm110ZhongwenWendang/img/apple-touch-icon.png
Storm110ZhongwenWendang/img/cancelfullscreen.png
Storm110ZhongwenWendang/img/close.png
Storm110ZhongwenWendang/img/fullscreen.png
Storm110ZhongwenWendang/img/loader.gif
Storm110ZhongwenWendang/img/menu-icon.png
Storm110ZhongwenWendang/img/save.png
Storm110ZhongwenWendang/img/saved.png
Storm110ZhongwenWendang/img/settings-s.png
Storm110ZhongwenWendang/img/settings.png
Storm110ZhongwenWendang/img/star.png
Storm110ZhongwenWendang/js/__init__.py
Storm110ZhongwenWendang/js/epub.js
Storm110ZhongwenWendang/js/epub.min.js
Storm110ZhongwenWendang/js/epub.min.map
Storm110ZhongwenWendang/js/hooks.min.js
Storm110ZhongwenWendang/js/hooks.min.map
Storm110ZhongwenWendang/js/reader.js
Storm110ZhongwenWendang/js/reader.js.map
Storm110ZhongwenWendang/js/reader.min.js
Storm110ZhongwenWendang/js/reader.min.map
Storm110ZhongwenWendang/js/hooks/__init__.py
Storm110ZhongwenWendang/js/hooks/extensions/__init__.py
Storm110ZhongwenWendang/js/hooks/extensions/highlight.js
Storm110ZhongwenWendang/js/libs/__init__.py
Storm110ZhongwenWendang/js/libs/jquery.min.js
Storm110ZhongwenWendang/js/libs/localforage.min.js
Storm110ZhongwenWendang/js/libs/screenfull.js
Storm110ZhongwenWendang/js/libs/screenfull.min.js
storm_1_1_0_zhongwen_wendang-2024.3.2.0.dist-info/METADATA
storm_1_1_0_zhongwen_wendang-2024.3.2.0.dist-info/WHEEL
storm_1_1_0_zhongwen_wendang-2024.3.2.0.dist-info/entry_points.txt
storm_1_1_0_zhongwen_wendang-2024.3.2.0.dist-info/top_level.txt
storm_1_1_0_zhongwen_wendang-2024.3.2.0.dist-info/RECORD
